pylexibank/__init__.py
pylexibank/cldf-metadata.json
pylexibank/cldf.py
pylexibank/cli_util.py
pylexibank/dataset.py
pylexibank/db.py
pylexibank/forms.py
pylexibank/lingpy_util.py
pylexibank/metadata.py
pylexibank/models.py
pylexibank/profile.py
pylexibank/report.py
pylexibank/scaffold.py
pylexibank/transcription.py
pylexibank/util.py
pylexibank/commands/__init__.py
pylexibank/commands/check.py
pylexibank/commands/check_languages.py
pylexibank/commands/check_lexibank.py
pylexibank/commands/check_phonotactics.py
pylexibank/commands/check_profile.py
pylexibank/commands/consonant_clusters.py
pylexibank/commands/db.py
pylexibank/commands/format_profile.py
pylexibank/commands/init_profile.py
pylexibank/commands/language_profiles.py
pylexibank/commands/load.py
pylexibank/commands/ls.py
pylexibank/commands/makecldf.py
pylexibank/commands/readme.py
pylexibank/commands/unload.py
pylexibank/dataset_templates/__init__.py
pylexibank/dataset_templates/lexibank_combined/lexibank_+id+.py_tmpl
pylexibank/dataset_templates/lexibank_simple/.gitignore
pylexibank/dataset_templates/lexibank_simple/.travis.yml
pylexibank/dataset_templates/lexibank_simple/CONTRIBUTORS.md
pylexibank/dataset_templates/lexibank_simple/lexibank_+id+.py_tmpl
pylexibank/dataset_templates/lexibank_simple/setup.py_tmpl
pylexibank/providers/__init__.py
pylexibank/providers/abvd.py
pylexibank/providers/clld.py
pylexibank/providers/qlc.py
pylexibank/providers/sndcmp.py
pylexibank/providers/tob.py
pylexibank-3.5.0.dist-info/LICENSE
pylexibank-3.5.0.dist-info/METADATA
pylexibank-3.5.0.dist-info/WHEEL
pylexibank-3.5.0.dist-info/entry_points.txt
pylexibank-3.5.0.dist-info/top_level.txt
pylexibank-3.5.0.dist-info/RECORD
