Metadata-Version: 2.1
Name: pylexibank
Version: 3.5.0
Summary: Python library implementing the lexibank workbench
Home-page: https://github.com/lexibank/pylexibank
Author: Robert Forkel
Author-email: dlce.rdm@eva.mpg.de
Project-URL: Bug Tracker, https://github.com/lexibank/pylexibank/issues
Platform: any
Classifier: Development Status :: 5 - Production/Stable
Classifier: Intended Audience :: Developers
Classifier: Intended Audience :: Science/Research
Classifier: Natural Language :: English
Classifier: Operating System :: OS Independent
Classifier: Programming Language :: Python :: 3
Classifier: Programming Language :: Python :: 3.8
Classifier: Programming Language :: Python :: 3.9
Classifier: Programming Language :: Python :: 3.10
Classifier: Programming Language :: Python :: 3.11
Classifier: Programming Language :: Python :: 3.12
Classifier: Programming Language :: Python :: Implementation :: CPython
Classifier: Programming Language :: Python :: Implementation :: PyPy
Classifier: License :: OSI Approved :: Apache Software License
Requires-Python: >=3.8
Provides-Extra: dev
Provides-Extra: test
License-File: LICENSE
